README.md
setup.py
gpgrecord/__init__.py
gpgrecord/test_.py
gpgrecord.egg-info/PKG-INFO
gpgrecord.egg-info/SOURCES.txt
gpgrecord.egg-info/dependency_links.txt
gpgrecord.egg-info/not-zip-safe
gpgrecord.egg-info/requires.txt
gpgrecord.egg-info/top_level.txt