Metadata-Version: 2.1
Name: gpgrecord
Version: 0.0.5
Summary: Encrypt/Decrypt interface for GPG record compatiable with JSON via base64.
Home-page: https://github.com/wefindx/gpgrecord
Author: Mindey
Author-email: mindey@qq.com
License: MIT
Platform: UNKNOWN
Provides-Extra: test
